django_fastapi/__init__.py
django_fastapi/apps.py
django_fastapi/asgi.py
django_fastapi/registry.py
django_fastapi/settings.py
django_fastapi/shortcuts.py
django_fastapi/utils.py
django_fastapi/wsgi.py
django_fastapi_bridge-0.2.dist-info/LICENSE.txt
django_fastapi_bridge-0.2.dist-info/METADATA
django_fastapi_bridge-0.2.dist-info/WHEEL
django_fastapi_bridge-0.2.dist-info/top_level.txt
django_fastapi_bridge-0.2.dist-info/RECORD
