Metadata-Version: 2.1
Name: django-fastapi-bridge
Version: 0.2
Summary: Build FastAPI app top of Django
Author-email: Marcin Nowak <marcin.j.nowak@gmail.com>
License: Copyright 2023 Marcin Nowak <marcin.j.nowak.gmail.com>
Project-URL: homepage, https://gitlab.com/marcinjn/django-fastapi
Project-URL: repository, https://gitlab.com/marcinjn/django-fastapi
Keywords: web,python,django,fastapi,wrapper,bridge
Classifier: Development Status :: 4 - Beta
Classifier: Environment :: Web Environment
Classifier: Framework :: Django
Classifier: Framework :: Django :: 3.1
Classifier: Framework :: Django :: 3.2
Classifier: Framework :: Django :: 4.0
Classifier: Framework :: Django :: 4.1
Classifier: Framework :: Django :: 4.2
Classifier: License :: OSI Approved :: ISC License (ISCL)
Classifier: Operating System :: OS Independent
Classifier: Programming Language :: Python
Classifier: Programming Language :: Python :: 3.9
Classifier: Programming Language :: Python :: 3.10
Classifier: Programming Language :: Python :: 3.11
Classifier: Topic :: Internet :: WWW/HTTP
Classifier: Topic :: Software Development :: Libraries :: Python Modules
Classifier: Intended Audience :: Developers
Requires-Python: >=3.9
License-File: LICENSE.txt
Requires-Dist: fastapi
Requires-Dist: django
Requires-Dist: a2wsgi
Provides-Extra: daphne
Requires-Dist: daphne ; extra == 'daphne'
